django2_postgres/__init__.py
django2_postgres/geos_patch.py
django2_postgres/operations.py
django2_postgres/psycopg_patch.py
django2_postgres_backport-0.0.3.dist-info/licenses/LICENSE
django2_postgres_backport-0.0.3.dist-info/METADATA
django2_postgres_backport-0.0.3.dist-info/WHEEL
django2_postgres_backport-0.0.3.dist-info/top_level.txt
django2_postgres_backport-0.0.3.dist-info/RECORD
